dynadbobjectstore.py
setup.py
dynadbobjectstore.egg-info/PKG-INFO
dynadbobjectstore.egg-info/SOURCES.txt
dynadbobjectstore.egg-info/dependency_links.txt
dynadbobjectstore.egg-info/requires.txt
dynadbobjectstore.egg-info/top_level.txt